moresim/__init__.py
MoreSim-0.0.1.dist-info/METADATA
MoreSim-0.0.1.dist-info/WHEEL
MoreSim-0.0.1.dist-info/top_level.txt
MoreSim-0.0.1.dist-info/RECORD
