Metadata-Version: 2.1
Name: MoreSim
Version: 0.0.1
Summary: The funniest joke in the world
Home-page: http://github.com/raimon-fa/
Author: Raimon Fabregat
Author-email: raimon.fa@gmail.com
License: MIT
Platform: UNKNOWN
Classifier: Programming Language :: Python :: 3
Classifier: License :: OSI Approved :: MIT License
Classifier: Operating System :: OS Independent
